{
  "dataset_name": "VOC07",
  "seed_set": {
    "image_set_idx": [
      "009863",
      "007208",
      "007821",
      "009900",
      "002533",
      "002643",
      "007374",
      "005020",
      "001980",
      "009106",
      "002691",
      "005756",
      "001360",
      "008706",
      "007475"
    ],
    "class_dist": []
  },
  "val_set": {
    "image_set_idx": [
      "003636",
      "002116",
      "006206",
      "004244",
      "000245",
      "003256",
      "009839",
      "007663",
      "006330",
      "000545"
    ],
    "class_dist": []
  },
  "train_set": [
    "009863",
    "007208",
    "007821",
    "009900",
    "002533",
    "002643",
    "007374",
    "005020",
    "001980",
    "009106",
    "002691",
    "005756",
    "001360",
    "008706",
    "007475"
  ]
}